TuijianXitongYushangShenduXuexi150/README.md
TuijianXitongYushangShenduXuexi150/__init__.py
TuijianXitongYushangShenduXuexi150/__main__.py
TuijianXitongYushangShenduXuexi150/file.epub
TuijianXitongYushangShenduXuexi150/index.html
TuijianXitongYushangShenduXuexi150/css/__init__.py
TuijianXitongYushangShenduXuexi150/css/annotations.css
TuijianXitongYushangShenduXuexi150/css/main.css
TuijianXitongYushangShenduXuexi150/css/normalize.css
TuijianXitongYushangShenduXuexi150/css/popup.css
TuijianXitongYushangShenduXuexi150/font/__init__.py
TuijianXitongYushangShenduXuexi150/font/fontello.eot
TuijianXitongYushangShenduXuexi150/font/fontello.svg
TuijianXitongYushangShenduXuexi150/font/fontello.ttf
TuijianXitongYushangShenduXuexi150/font/fontello.woff
TuijianXitongYushangShenduXuexi150/img/__init__.py
TuijianXitongYushangShenduXuexi150/img/annotator-glyph-sprite.png
TuijianXitongYushangShenduXuexi150/img/annotator-icon-sprite.png
TuijianXitongYushangShenduXuexi150/img/apple-touch-icon.png
TuijianXitongYushangShenduXuexi150/img/cancelfullscreen.png
TuijianXitongYushangShenduXuexi150/img/close.png
TuijianXitongYushangShenduXuexi150/img/fullscreen.png
TuijianXitongYushangShenduXuexi150/img/loader.gif
TuijianXitongYushangShenduXuexi150/img/menu-icon.png
TuijianXitongYushangShenduXuexi150/img/save.png
TuijianXitongYushangShenduXuexi150/img/saved.png
TuijianXitongYushangShenduXuexi150/img/settings-s.png
TuijianXitongYushangShenduXuexi150/img/settings.png
TuijianXitongYushangShenduXuexi150/img/star.png
TuijianXitongYushangShenduXuexi150/js/__init__.py
TuijianXitongYushangShenduXuexi150/js/epub.js
TuijianXitongYushangShenduXuexi150/js/epub.min.js
TuijianXitongYushangShenduXuexi150/js/epub.min.map
TuijianXitongYushangShenduXuexi150/js/hooks.min.js
TuijianXitongYushangShenduXuexi150/js/hooks.min.map
TuijianXitongYushangShenduXuexi150/js/reader.js
TuijianXitongYushangShenduXuexi150/js/reader.js.map
TuijianXitongYushangShenduXuexi150/js/reader.min.js
tuijian_xitong_yushang_shendu_xuexi_1_50-2024.3.5.0.dist-info/METADATA
tuijian_xitong_yushang_shendu_xuexi_1_50-2024.3.5.0.dist-info/WHEEL
tuijian_xitong_yushang_shendu_xuexi_1_50-2024.3.5.0.dist-info/entry_points.txt
tuijian_xitong_yushang_shendu_xuexi_1_50-2024.3.5.0.dist-info/top_level.txt
tuijian_xitong_yushang_shendu_xuexi_1_50-2024.3.5.0.dist-info/RECORD
